__init__.py
BuildScript_RyzeYang/BuildHelper.py
BuildScript_RyzeYang/EncryptDllHelper.py
BuildScript_RyzeYang/FileVersionHelper.py
BuildScript_RyzeYang/main.py
BuildScript_RyzeYang-1.0.0.dist-info/LICENSE
BuildScript_RyzeYang-1.0.0.dist-info/METADATA
BuildScript_RyzeYang-1.0.0.dist-info/WHEEL
BuildScript_RyzeYang-1.0.0.dist-info/top_level.txt
BuildScript_RyzeYang-1.0.0.dist-info/RECORD
