Metadata-Version: 2.1
Name: BuildScript_RyzeYang
Version: 1.0.0
Summary: 安装包命令执行脚本
Author-email: Yang GenJie <yang_genjie@126.com>
Project-URL: Homepage, https://github.com/pypa/sampleproject
Project-URL: Bug Tracker, https://github.com/pypa/sampleproject/issues
Classifier: Programming Language :: Python :: 3
Classifier: License :: OSI Approved :: MIT License
Classifier: Operating System :: OS Independent
Requires-Python: >=3.7
License-File: LICENSE
